{
  "LastID": 40,
  "D01": {
    "type": "Deluxe",
    "dateBooking": [],
    "bookingData": []
  },
  "D02": {
    "type": "Deluxe",
    "dateBooking": [],
    "bookingData": []
  },
  "D03": {
    "type": "Deluxe",
    "dateBooking": [
      "2021-12-24"
    ],
    "bookingData": [
      {
        "Name": "sdfdsa",
        "Surname": "asdffdfsa",
        "tel": "0000000000",
        "roomType": "Deluxe",
        "roomID": "D03",
        "dateIn": "2021-12-24",
        "dateOut": "2021-12-25",
        "id": 35
      }
    ]
  },
  "D04": {
    "type": "Deluxe",
    "dateBooking": [],
    "bookingData": []
  },
  "D05": {
    "type": "Deluxe",
    "dateBooking": [],
    "bookingData": []
  },
  "N01": {
    "type": "Normal",
    "dateBooking": [],
    "bookingData": []
  },
  "N02": {
    "type": "Normal",
    "dateBooking": [],
    "bookingData": []
  },
  "N03": {
    "type": "Normal",
    "dateBooking": [
      "2021-12-20"
    ],
    "bookingData": [
      {
        "Name": "asdf",
        "Surname": "asdf",
        "tel": "0000000000",
        "roomType": "Normal",
        "roomID": "N03",
        "dateIn": "2021-12-20",
        "dateOut": "2021-12-21",
        "id": 34
      }
    ]
  },
  "N04": {
    "type": "Normal",
    "dateBooking": [],
    "bookingData": []
  },
  "N05": {
    "type": "Normal",
    "dateBooking": [],
    "bookingData": []
  },
  "T01": {
    "type": "Twin",
    "dateBooking": [],
    "bookingData": []
  },
  "T02": {
    "type": "Twin",
    "dateBooking": [],
    "bookingData": []
  },
  "T03": {
    "type": "Twin",
    "dateBooking": [],
    "bookingData": []
  },
  "T04": {
    "type": "Twin",
    "dateBooking": [],
    "bookingData": []
  },
  "T05": {
    "type": "Twin",
    "dateBooking": [],
    "bookingData": []
  }
}